MANIFEST.in
README.rst
setup.py
webhdfspy/__init__.py
webhdfspy/webhdfspy.py
webhdfspy.egg-info/PKG-INFO
webhdfspy.egg-info/SOURCES.txt
webhdfspy.egg-info/dependency_links.txt
webhdfspy.egg-info/not-zip-safe
webhdfspy.egg-info/pbr.json
webhdfspy.egg-info/requires.txt
webhdfspy.egg-info/top_level.txt