Metadata-Version: 1.1
Name: webhdfspy
Version: 0.3.5
Summary: A wrapper library to access Hadoop HTTP REST API
Home-page: https://github.com/fasouto/webhdfspy
Author: Fabio Souto
Author-email: fabio@fabiosouto.me
License: MIT
Keywords: hadoop webhdfs
Platform: UNKNOWN
Classifier: Development Status :: 4 - Beta
Classifier: Intended Audience :: Developers
Classifier: License :: OSI Approved :: MIT License
Classifier: Programming Language :: Python :: 2.7
Classifier: Topic :: Software Development :: Libraries
